{	"response": {		"players": [			{				"steamid": "76561198171037411",				"communityvisibilitystate": 3,				"profilestate": 1,				"personaname": "AA",				"lastlogoff": 1511375843,				"commentpermission": 1,				"profileurl": "http://steamcommunity.com/profiles/76561198171037411/",				"avatar": "https://steamcdn-a.akamaihd.net/steamcommunity/public/images/avatars/c7/c7401905e52e762b52dc3ca696a2b97139001dae.jpg",				"avatarmedium": "https://steamcdn-a.akamaihd.net/steamcommunity/public/images/avatars/c7/c7401905e52e762b52dc3ca696a2b97139001dae_medium.jpg",				"avatarfull": "https://steamcdn-a.akamaihd.net/steamcommunity/public/images/avatars/c7/c7401905e52e762b52dc3ca696a2b97139001dae_full.jpg",				"personastate": 1,				"realname": "Andrey",				"primaryclanid": "103582791429521408",				"timecreated": 1419870823,				"personastateflags": 0,				"gameextrainfo": "CS2D",				"gameid": "666220",				"loccountrycode": "UA"			}		]			}}
