{	"response": {		"players": [			{				"steamid": "76561198123223871",				"communityvisibilitystate": 3,				"profilestate": 1,				"personaname": "PhantomX9",				"lastlogoff": 1511468893,				"profileurl": "http://steamcommunity.com/profiles/76561198123223871/",				"avatar": "https://steamcdn-a.akamaihd.net/steamcommunity/public/images/avatars/8b/8babfb0458e647b6895c682eaddaed2ad94812e4.jpg",				"avatarmedium": "https://steamcdn-a.akamaihd.net/steamcommunity/public/images/avatars/8b/8babfb0458e647b6895c682eaddaed2ad94812e4_medium.jpg",				"avatarfull": "https://steamcdn-a.akamaihd.net/steamcommunity/public/images/avatars/8b/8babfb0458e647b6895c682eaddaed2ad94812e4_full.jpg",				"personastate": 1,				"primaryclanid": "103582791441349925",				"timecreated": 1389970778,				"personastateflags": 0,				"gameextrainfo": "CS2D",				"gameid": "666220",				"loccountrycode": "CZ"			}		]			}}
